setup.py
tcked/__init__.py
tcked/conf.py
tcked/fields.py
tcked/tests.py
tcked/widgets.py
twentytab_tcked.egg-info/PKG-INFO
twentytab_tcked.egg-info/SOURCES.txt
twentytab_tcked.egg-info/dependency_links.txt
twentytab_tcked.egg-info/requires.txt
twentytab_tcked.egg-info/top_level.txt