Metadata-Version: 1.0
Name: twentytab-tcked
Version: 0.1
Summary: A django application that use cked as texteditor. It update RichTextField with config parameter
Home-page: https://github.com/20tab/twentytab-tcked
Author: 20tab S.r.l.
Author-email: info@20tab.com
License: MIT License
Platform: UNKNOWN
